{"devicePlatform":"","logFolder":"C:\\Users\\asalah\\git\\Training_1\\Reports\\TS_Locations\\20190102_162637","runData":{"hostName":"asalah - LPALXY0442.ejadaalex.local","os":"Windows 10 64bit","katalonVersion":"5.8.6.1","browser":"Chrome 71.0.3578.98","hostAddress":"192.168.3.57","sessionId":"8ba8176f45a3c88aeb19db4ac4ec1441","seleniumVersion":"3.7.1","proxyInformation":"ProxyInformation{proxyOption\u003dNO_PROXY, proxyServerType\u003dHTTP, password\u003d, proxyServerAddress\u003d, proxyServerPort\u003d0}","platform":"Windows 10"},"type":"TEST_SUITE","name":"TS_Locations","id":"Test Suites/TS_Locations","source":"","message":"Test Cases/Orange_Website/TC_Locations","description":"","startTime":1546439200836,"endTime":1546439226730,"childRecords":[{"isOptional":false,"type":"TEST_CASE","name":"Test Cases/Orange_Website/Login Screen","id":"Test Cases/Orange_Website/Login Screen","source":"C:\\\\Users\\\\asalah\\\\git\\\\Training_1\\\\Test Cases\\\\Orange_Website\\\\Login Screen.tc","message":"Test Cases/Orange_Website/Login Screen","description":"","startTime":1546439201512,"endTime":1546439212670,"childRecords":[{"testStatus":{"stackTrace":"","statusValue":"INFO"},"type":"MESSAGE","name":"","message":"Evaluating variables for test case","startTime":1546439201562,"endTime":0,"childRecords":[],"interuppted":false},{"index":1,"isIgnoredIfFailed":false,"type":"TEST_STEP","name":"openBrowser","message":"Browser is opened with url: \u0027https://opensource-demo.orangehrmlive.com/index.php/auth/login\u0027","description":"","startTime":1546439202332,"endTime":1546439209632,"childRecords":[{"testStatus":{"stackTrace":"","statusValue":"PASSED"},"type":"MESSAGE","name":"","message":"Browser is opened with url: \u0027https://opensource-demo.orangehrmlive.com/index.php/auth/login\u0027","startTime":1546439209629,"endTime":0,"childRecords":[],"interuppted":false}],"interuppted":false},{"index":2,"isIgnoredIfFailed":false,"type":"TEST_STEP","name":"setText","message":"Text \u0027Admin\u0027 is set on object \u0027Object Repository/Orange/Login/Username\u0027","description":"","startTime":1546439209633,"endTime":1546439210141,"childRecords":[{"testStatus":{"stackTrace":"","statusValue":"PASSED"},"type":"MESSAGE","name":"","message":"Text \u0027Admin\u0027 is set on object \u0027Object Repository/Orange/Login/Username\u0027","startTime":1546439210140,"endTime":0,"childRecords":[],"interuppted":false}],"interuppted":false},{"index":3,"isIgnoredIfFailed":false,"type":"TEST_STEP","name":"setText","message":"Text \u0027admin123\u0027 is set on object \u0027Object Repository/Orange/Login/Password\u0027","description":"","startTime":1546439210142,"endTime":1546439210308,"childRecords":[{"testStatus":{"stackTrace":"","statusValue":"PASSED"},"type":"MESSAGE","name":"","message":"Text \u0027admin123\u0027 is set on object \u0027Object Repository/Orange/Login/Password\u0027","startTime":1546439210307,"endTime":0,"childRecords":[],"interuppted":false}],"interuppted":false},{"index":4,"isIgnoredIfFailed":false,"type":"TEST_STEP","name":"click","message":"Object: \u0027Object Repository/Orange/Login/Login\u0027 is clicked on","description":"","startTime":1546439210309,"endTime":1546439212667,"childRecords":[{"testStatus":{"stackTrace":"","statusValue":"PASSED"},"type":"MESSAGE","name":"","message":"Object: \u0027Object Repository/Orange/Login/Login\u0027 is clicked on","startTime":1546439212665,"endTime":0,"childRecords":[],"interuppted":false}],"interuppted":false},{"testStatus":{"stackTrace":"","statusValue":"PASSED"},"type":"MESSAGE","name":"","message":"Test Cases/Orange_Website/Login Screen","startTime":1546439212668,"endTime":0,"childRecords":[],"interuppted":false}],"interuppted":false},{"isOptional":false,"type":"TEST_CASE","name":"Test Cases/Orange_Website/TC_Locations","id":"Test Cases/Orange_Website/TC_Locations","source":"C:\\\\Users\\\\asalah\\\\git\\\\Training_1\\\\Test Cases\\\\Orange_Website\\\\TC_Locations.tc","message":"Test Cases/Orange_Website/TC_Locations","description":"","startTime":1546439212680,"endTime":1546439225883,"childRecords":[{"testStatus":{"stackTrace":"","statusValue":"INFO"},"type":"MESSAGE","name":"","message":"Evaluating variables for test case","startTime":1546439212702,"endTime":0,"childRecords":[],"interuppted":false},{"index":1,"isIgnoredIfFailed":false,"type":"TEST_STEP","name":"openBrowser","message":"Browser is opened with url: \u0027https://opensource-demo.orangehrmlive.com/index.php/auth/login\u0027","description":"","startTime":1546439212975,"endTime":1546439218827,"childRecords":[{"testStatus":{"stackTrace":"","statusValue":"WARNING"},"type":"MESSAGE","name":"","message":"A browser is already opened. Closing browser and opening a new one","startTime":1546439212977,"endTime":0,"childRecords":[],"interuppted":false},{"testStatus":{"stackTrace":"","statusValue":"PASSED"},"type":"MESSAGE","name":"","message":"Browser is opened with url: \u0027https://opensource-demo.orangehrmlive.com/index.php/auth/login\u0027","startTime":1546439218825,"endTime":0,"childRecords":[],"interuppted":false}],"interuppted":false},{"index":2,"isIgnoredIfFailed":false,"type":"TEST_STEP","name":"setText","message":"Text \u0027Admin\u0027 is set on object \u0027Object Repository/Orange/Login/Username\u0027","description":"","startTime":1546439218828,"endTime":1546439219038,"childRecords":[{"testStatus":{"stackTrace":"","statusValue":"PASSED"},"type":"MESSAGE","name":"","message":"Text \u0027Admin\u0027 is set on object \u0027Object Repository/Orange/Login/Username\u0027","startTime":1546439219037,"endTime":0,"childRecords":[],"interuppted":false}],"interuppted":false},{"index":3,"isIgnoredIfFailed":false,"type":"TEST_STEP","name":"setText","message":"Text \u0027admin123\u0027 is set on object \u0027Object Repository/Orange/Login/Password\u0027","description":"","startTime":1546439219039,"endTime":1546439219214,"childRecords":[{"testStatus":{"stackTrace":"","statusValue":"PASSED"},"type":"MESSAGE","name":"","message":"Text \u0027admin123\u0027 is set on object \u0027Object Repository/Orange/Login/Password\u0027","startTime":1546439219213,"endTime":0,"childRecords":[],"interuppted":false}],"interuppted":false},{"index":4,"isIgnoredIfFailed":false,"type":"TEST_STEP","name":"click","message":"Object: \u0027Object Repository/Orange/Login/Login\u0027 is clicked on","description":"","startTime":1546439219214,"endTime":1546439220970,"childRecords":[{"testStatus":{"stackTrace":"","statusValue":"PASSED"},"type":"MESSAGE","name":"","message":"Object: \u0027Object Repository/Orange/Login/Login\u0027 is clicked on","startTime":1546439220969,"endTime":0,"childRecords":[],"interuppted":false}],"interuppted":false},{"index":5,"isIgnoredIfFailed":false,"type":"TEST_STEP","name":"navigateToUrl","message":"Navigate to \u0027https://opensource-demo.orangehrmlive.com/index.php/admin/viewLocations\u0027 successfully","description":"","startTime":1546439220970,"endTime":1546439222580,"childRecords":[{"testStatus":{"stackTrace":"","statusValue":"PASSED"},"type":"MESSAGE","name":"","message":"Navigate to \u0027https://opensource-demo.orangehrmlive.com/index.php/admin/viewLocations\u0027 successfully","startTime":1546439222579,"endTime":0,"childRecords":[],"interuppted":false}],"interuppted":false},{"index":6,"isIgnoredIfFailed":false,"type":"TEST_STEP","name":"click","message":"Object: \u0027Object Repository/Orange/Locations/btn_select\u0027 is clicked on","description":"","startTime":1546439222580,"endTime":1546439223313,"childRecords":[{"testStatus":{"stackTrace":"","statusValue":"PASSED"},"type":"MESSAGE","name":"","message":"Object: \u0027Object Repository/Orange/Locations/btn_select\u0027 is clicked on","startTime":1546439223312,"endTime":0,"childRecords":[],"interuppted":false}],"interuppted":false},{"index":7,"isIgnoredIfFailed":false,"type":"TEST_STEP","name":"click","message":"Object: \u0027Object Repository/Orange/Locations/btn_Edit\u0027 is clicked on","description":"","startTime":1546439223314,"endTime":1546439223488,"childRecords":[{"testStatus":{"stackTrace":"","statusValue":"PASSED"},"type":"MESSAGE","name":"","message":"Object: \u0027Object Repository/Orange/Locations/btn_Edit\u0027 is clicked on","startTime":1546439223487,"endTime":0,"childRecords":[],"interuppted":false}],"interuppted":false},{"index":8,"isIgnoredIfFailed":false,"type":"TEST_STEP","name":"pk_Functions.CS_CheckMatching.CheckMatching","message":"pk_Functions.CS_CheckMatching.CheckMatching is PASSED","description":"","startTime":1546439223488,"endTime":1546439225883,"childRecords":[{"testStatus":{"stackTrace":"","statusValue":"PASSED"},"type":"MESSAGE","name":"","message":"Attribute \u0027value\u0027 of object \u0027\u0027 is: \u0027Azza\u0027","startTime":1546439225002,"endTime":0,"childRecords":[],"interuppted":false},{"testStatus":{"stackTrace":"","statusValue":"PASSED"},"type":"MESSAGE","name":"","message":"Actual text \u0027Azza\u0027 and expected text \u0027Azza\u0027 are matched ","startTime":1546439225141,"endTime":0,"childRecords":[],"interuppted":false},{"testStatus":{"stackTrace":"","statusValue":"PASSED"},"type":"MESSAGE","name":"","message":"Attribute \u0027value\u0027 of object \u0027\u0027 is: \u0027EG\u0027","startTime":1546439225194,"endTime":0,"childRecords":[],"interuppted":false},{"testStatus":{"stackTrace":"","statusValue":"PASSED"},"type":"MESSAGE","name":"","message":"Actual text \u0027EG\u0027 and expected text \u0027EG\u0027 are matched ","startTime":1546439225242,"endTime":0,"childRecords":[],"interuppted":false},{"testStatus":{"stackTrace":"","statusValue":"PASSED"},"type":"MESSAGE","name":"","message":"Attribute \u0027value\u0027 of object \u0027\u0027 is: \u0027XX\u0027","startTime":1546439225287,"endTime":0,"childRecords":[],"interuppted":false},{"testStatus":{"stackTrace":"","statusValue":"PASSED"},"type":"MESSAGE","name":"","message":"Actual text \u0027XX\u0027 and expected text \u0027XX\u0027 are matched ","startTime":1546439225333,"endTime":0,"childRecords":[],"interuppted":false},{"testStatus":{"stackTrace":"","statusValue":"PASSED"},"type":"MESSAGE","name":"","message":"Attribute \u0027value\u0027 of object \u0027\u0027 is: \u0027Alexandria\u0027","startTime":1546439225372,"endTime":0,"childRecords":[],"interuppted":false},{"testStatus":{"stackTrace":"","statusValue":"PASSED"},"type":"MESSAGE","name":"","message":"Actual text \u0027Alexandria\u0027 and expected text \u0027Alexandria\u0027 are matched ","startTime":1546439225418,"endTime":0,"childRecords":[],"interuppted":false},{"testStatus":{"stackTrace":"","statusValue":"PASSED"},"type":"MESSAGE","name":"","message":"Attribute \u0027value\u0027 of object \u0027\u0027 is: \u0027\u0027","startTime":1546439225471,"endTime":0,"childRecords":[],"interuppted":false},{"testStatus":{"stackTrace":"","statusValue":"PASSED"},"type":"MESSAGE","name":"","message":"Actual text \u0027\u0027 and expected text \u0027\u0027 are matched ","startTime":1546439225512,"endTime":0,"childRecords":[],"interuppted":false},{"testStatus":{"stackTrace":"","statusValue":"PASSED"},"type":"MESSAGE","name":"","message":"Attribute \u0027value\u0027 of object \u0027\u0027 is: \u002712012\u0027","startTime":1546439225559,"endTime":0,"childRecords":[],"interuppted":false},{"testStatus":{"stackTrace":"","statusValue":"PASSED"},"type":"MESSAGE","name":"","message":"Actual text \u002712012\u0027 and expected text \u002712012\u0027 are matched ","startTime":1546439225622,"endTime":0,"childRecords":[],"interuppted":false},{"testStatus":{"stackTrace":"","statusValue":"PASSED"},"type":"MESSAGE","name":"","message":"Attribute \u0027value\u0027 of object \u0027\u0027 is: \u002701129211656\u0027","startTime":1546439225667,"endTime":0,"childRecords":[],"interuppted":false},{"testStatus":{"stackTrace":"","statusValue":"PASSED"},"type":"MESSAGE","name":"","message":"Actual text \u002701129211656\u0027 and expected text \u002701129211656\u0027 are matched ","startTime":1546439225711,"endTime":0,"childRecords":[],"interuppted":false},{"testStatus":{"stackTrace":"","statusValue":"PASSED"},"type":"MESSAGE","name":"","message":"Attribute \u0027value\u0027 of object \u0027\u0027 is: \u0027\u0027","startTime":1546439225758,"endTime":0,"childRecords":[],"interuppted":false},{"testStatus":{"stackTrace":"","statusValue":"PASSED"},"type":"MESSAGE","name":"","message":"Actual text \u0027\u0027 and expected text \u0027\u0027 are matched ","startTime":1546439225795,"endTime":0,"childRecords":[],"interuppted":false},{"testStatus":{"stackTrace":"","statusValue":"PASSED"},"type":"MESSAGE","name":"","message":"Attribute \u0027value\u0027 of object \u0027\u0027 is: \u0027first location\u0027","startTime":1546439225848,"endTime":0,"childRecords":[],"interuppted":false},{"testStatus":{"stackTrace":"","statusValue":"PASSED"},"type":"MESSAGE","name":"","message":"Actual text \u0027first location\u0027 and expected text \u0027first location\u0027 are matched ","startTime":1546439225882,"endTime":0,"childRecords":[],"interuppted":false},{"testStatus":{"stackTrace":"","statusValue":"PASSED"},"type":"MESSAGE","name":"","message":"pk_Functions.CS_CheckMatching.CheckMatching is PASSED","startTime":1546439225882,"endTime":0,"childRecords":[],"interuppted":false}],"interuppted":false},{"testStatus":{"stackTrace":"","statusValue":"PASSED"},"type":"MESSAGE","name":"","message":"Test Cases/Orange_Website/TC_Locations","startTime":1546439225883,"endTime":0,"childRecords":[],"interuppted":false}],"interuppted":false}],"interuppted":false}