{"devicePlatform":"","logFolder":"C:\\Users\\aeibrahim\\git\\Training_1\\Reports\\TS_OrangeWebUsingKeywords\\20190103_162439","runData":{"hostName":"aeibrahim - LPALXY0477.ejadaalex.local","os":"Windows 10 64bit","katalonVersion":"5.8.6.1","browser":"Chrome 71.0.3578.98","hostAddress":"192.168.3.64","sessionId":"dab79bbe05dda390db82172c58140152","seleniumVersion":"3.7.1","proxyInformation":"ProxyInformation{proxyOption\u003dNO_PROXY, proxyServerType\u003dHTTP, password\u003d, proxyServerAddress\u003d, proxyServerPort\u003d0}","platform":"Windows 10"},"type":"TEST_SUITE","name":"TS_OrangeWebUsingKeywords","id":"Test Suites/TS_OrangeWebUsingKeywords","source":"","message":"Test Cases/Orange_Website_Using_Function/TC_AllPageComponent","description":"","startTime":1546525481171,"endTime":1546525513756,"childRecords":[{"isOptional":false,"type":"TEST_CASE","name":"Test Cases/Orange_Website_Using_Function/TC_AllPageComponent","id":"Test Cases/Orange_Website_Using_Function/TC_AllPageComponent","source":"C:\\\\Users\\\\aeibrahim\\\\git\\\\Training_1\\\\Test Cases\\\\Orange_Website_Using_Function\\\\TC_AllPageComponent.tc","message":"Test Cases/Orange_Website_Using_Function/TC_AllPageComponent","description":"","startTime":1546525481569,"endTime":1546525501174,"childRecords":[{"testStatus":{"stackTrace":"","statusValue":"INFO"},"type":"MESSAGE","name":"","message":"Evaluating variables for test case","startTime":1546525481597,"endTime":0,"childRecords":[],"interuppted":false},{"testStatus":{"stackTrace":"","statusValue":"INFO"},"type":"MESSAGE","name":"","message":"Variable \u0027CandidateName\u0027 is set to airamadan","startTime":1546525481606,"endTime":0,"childRecords":[],"interuppted":false},{"testStatus":{"stackTrace":"","statusValue":"INFO"},"type":"MESSAGE","name":"","message":"Variable \u0027JobTitle\u0027 is set to Account Clerk","startTime":1546525481607,"endTime":0,"childRecords":[],"interuppted":false},{"testStatus":{"stackTrace":"","statusValue":"INFO"},"type":"MESSAGE","name":"","message":"Variable \u0027WelcomeAdmin\u0027 is set to Logout","startTime":1546525481609,"endTime":0,"childRecords":[],"interuppted":false},{"index":1,"isIgnoredIfFailed":false,"type":"TEST_STEP","name":"pk_Functions.CS_Login.LoginFun","message":"pk_Functions.CS_Login.LoginFun is PASSED","description":"","startTime":1546525481992,"endTime":1546525498143,"childRecords":[{"testStatus":{"stackTrace":"","statusValue":"WARNING"},"type":"MESSAGE","name":"","message":"Test object id is null","startTime":1546525482000,"endTime":0,"childRecords":[],"interuppted":false},{"testStatus":{"stackTrace":"","statusValue":"PASSED"},"type":"MESSAGE","name":"","message":"Browser is opened with url: \u0027https://opensource-demo.orangehrmlive.com/index.php/auth/login\u0027","startTime":1546525493500,"endTime":0,"childRecords":[],"interuppted":false},{"testStatus":{"stackTrace":"","statusValue":"PASSED"},"type":"MESSAGE","name":"","message":"Text \u0027Admin\u0027 is set on object \u0027Object Repository/Orange/Login/Username\u0027","startTime":1546525493711,"endTime":0,"childRecords":[],"interuppted":false},{"testStatus":{"stackTrace":"","statusValue":"PASSED"},"type":"MESSAGE","name":"","message":"Text \u0027admin123\u0027 is set on object \u0027Object Repository/Orange/Login/Password\u0027","startTime":1546525493846,"endTime":0,"childRecords":[],"interuppted":false},{"testStatus":{"stackTrace":"","statusValue":"PASSED"},"type":"MESSAGE","name":"","message":"Object: \u0027Object Repository/Orange/Login/Login\u0027 is clicked on","startTime":1546525498142,"endTime":0,"childRecords":[],"interuppted":false},{"testStatus":{"stackTrace":"","statusValue":"PASSED"},"type":"MESSAGE","name":"","message":"pk_Functions.CS_Login.LoginFun is PASSED","startTime":1546525498143,"endTime":0,"childRecords":[],"interuppted":false}],"interuppted":false},{"index":2,"isIgnoredIfFailed":false,"type":"TEST_STEP","name":"click","message":"Object: \u0027Object Repository/Orange/Navigation/MNUITM_Recruitment\u0027 is clicked on","description":"","startTime":1546525498144,"endTime":1546525499741,"childRecords":[{"testStatus":{"stackTrace":"","statusValue":"PASSED"},"type":"MESSAGE","name":"","message":"Object: \u0027Object Repository/Orange/Navigation/MNUITM_Recruitment\u0027 is clicked on","startTime":1546525499741,"endTime":0,"childRecords":[],"interuppted":false}],"interuppted":false},{"index":3,"isIgnoredIfFailed":false,"type":"TEST_STEP","name":"pk_Functions.CS_TextLov.TextLovFun","message":"pk_Functions.CS_TextLov.TextLovFun is PASSED","description":"","startTime":1546525499742,"endTime":1546525501173,"childRecords":[{"testStatus":{"stackTrace":"","statusValue":"PASSED"},"type":"MESSAGE","name":"","message":"Text \u0027airamadan\u0027 is set on object \u0027\u0027","startTime":1546525500866,"endTime":0,"childRecords":[],"interuppted":false},{"testStatus":{"stackTrace":"","statusValue":"PASSED"},"type":"MESSAGE","name":"","message":"All options with label \u0027Account Clerk\u0027 are selected in object \u0027\u0027 ","startTime":1546525500988,"endTime":0,"childRecords":[],"interuppted":false},{"testStatus":{"stackTrace":"","statusValue":"PASSED"},"type":"MESSAGE","name":"","message":"pk_Functions.CS_TextLov.TextLovFun is PASSED","startTime":1546525501173,"endTime":0,"childRecords":[],"interuppted":false}],"interuppted":false},{"testStatus":{"stackTrace":"","statusValue":"PASSED"},"type":"MESSAGE","name":"","message":"Test Cases/Orange_Website_Using_Function/TC_AllPageComponent","startTime":1546525501173,"endTime":0,"childRecords":[],"interuppted":false}],"interuppted":false},{"isOptional":false,"type":"TEST_CASE","name":"Test Cases/Orange_Website_Using_Function/TC_AllPageComponent","id":"Test Cases/Orange_Website_Using_Function/TC_AllPageComponent","source":"C:\\\\Users\\\\aeibrahim\\\\git\\\\Training_1\\\\Test Cases\\\\Orange_Website_Using_Function\\\\TC_AllPageComponent.tc","message":"Test Cases/Orange_Website_Using_Function/TC_AllPageComponent","description":"","startTime":1546525501180,"endTime":1546525513755,"childRecords":[{"testStatus":{"stackTrace":"","statusValue":"INFO"},"type":"MESSAGE","name":"","message":"Evaluating variables for test case","startTime":1546525501187,"endTime":0,"childRecords":[],"interuppted":false},{"testStatus":{"stackTrace":"","statusValue":"INFO"},"type":"MESSAGE","name":"","message":"Variable \u0027CandidateName\u0027 is set to asmaa","startTime":1546525501187,"endTime":0,"childRecords":[],"interuppted":false},{"testStatus":{"stackTrace":"","statusValue":"INFO"},"type":"MESSAGE","name":"","message":"Variable \u0027JobTitle\u0027 is set to CEO","startTime":1546525501188,"endTime":0,"childRecords":[],"interuppted":false},{"testStatus":{"stackTrace":"","statusValue":"INFO"},"type":"MESSAGE","name":"","message":"Variable \u0027WelcomeAdmin\u0027 is set to About","startTime":1546525501188,"endTime":0,"childRecords":[],"interuppted":false},{"index":1,"isIgnoredIfFailed":false,"type":"TEST_STEP","name":"pk_Functions.CS_Login.LoginFun","message":"pk_Functions.CS_Login.LoginFun is PASSED","description":"","startTime":1546525501190,"endTime":1546525509560,"childRecords":[{"testStatus":{"stackTrace":"","statusValue":"WARNING"},"type":"MESSAGE","name":"","message":"Test object id is null","startTime":1546525501190,"endTime":0,"childRecords":[],"interuppted":false},{"testStatus":{"stackTrace":"","statusValue":"WARNING"},"type":"MESSAGE","name":"","message":"A browser is already opened. Closing browser and opening a new one","startTime":1546525501216,"endTime":0,"childRecords":[],"interuppted":false},{"testStatus":{"stackTrace":"","statusValue":"PASSED"},"type":"MESSAGE","name":"","message":"Browser is opened with url: \u0027https://opensource-demo.orangehrmlive.com/index.php/auth/login\u0027","startTime":1546525507722,"endTime":0,"childRecords":[],"interuppted":false},{"testStatus":{"stackTrace":"","statusValue":"PASSED"},"type":"MESSAGE","name":"","message":"Text \u0027Admin\u0027 is set on object \u0027Object Repository/Orange/Login/Username\u0027","startTime":1546525507851,"endTime":0,"childRecords":[],"interuppted":false},{"testStatus":{"stackTrace":"","statusValue":"PASSED"},"type":"MESSAGE","name":"","message":"Text \u0027admin123\u0027 is set on object \u0027Object Repository/Orange/Login/Password\u0027","startTime":1546525507965,"endTime":0,"childRecords":[],"interuppted":false},{"testStatus":{"stackTrace":"","statusValue":"PASSED"},"type":"MESSAGE","name":"","message":"Object: \u0027Object Repository/Orange/Login/Login\u0027 is clicked on","startTime":1546525509559,"endTime":0,"childRecords":[],"interuppted":false},{"testStatus":{"stackTrace":"","statusValue":"PASSED"},"type":"MESSAGE","name":"","message":"pk_Functions.CS_Login.LoginFun is PASSED","startTime":1546525509560,"endTime":0,"childRecords":[],"interuppted":false}],"interuppted":false},{"index":2,"isIgnoredIfFailed":false,"type":"TEST_STEP","name":"click","message":"Object: \u0027Object Repository/Orange/Navigation/MNUITM_Recruitment\u0027 is clicked on","description":"","startTime":1546525509561,"endTime":1546525513206,"childRecords":[{"testStatus":{"stackTrace":"","statusValue":"PASSED"},"type":"MESSAGE","name":"","message":"Object: \u0027Object Repository/Orange/Navigation/MNUITM_Recruitment\u0027 is clicked on","startTime":1546525513205,"endTime":0,"childRecords":[],"interuppted":false}],"interuppted":false},{"index":3,"isIgnoredIfFailed":false,"type":"TEST_STEP","name":"pk_Functions.CS_TextLov.TextLovFun","message":"pk_Functions.CS_TextLov.TextLovFun is PASSED","description":"","startTime":1546525513206,"endTime":1546525513754,"childRecords":[{"testStatus":{"stackTrace":"","statusValue":"PASSED"},"type":"MESSAGE","name":"","message":"Text \u0027asmaa\u0027 is set on object \u0027\u0027","startTime":1546525513443,"endTime":0,"childRecords":[],"interuppted":false},{"testStatus":{"stackTrace":"","statusValue":"PASSED"},"type":"MESSAGE","name":"","message":"All options with label \u0027CEO\u0027 are selected in object \u0027\u0027 ","startTime":1546525513562,"endTime":0,"childRecords":[],"interuppted":false},{"testStatus":{"stackTrace":"","statusValue":"PASSED"},"type":"MESSAGE","name":"","message":"pk_Functions.CS_TextLov.TextLovFun is PASSED","startTime":1546525513754,"endTime":0,"childRecords":[],"interuppted":false}],"interuppted":false},{"testStatus":{"stackTrace":"","statusValue":"PASSED"},"type":"MESSAGE","name":"","message":"Test Cases/Orange_Website_Using_Function/TC_AllPageComponent","startTime":1546525513755,"endTime":0,"childRecords":[],"interuppted":false}],"interuppted":false}],"interuppted":false}